textmater/__init__.py
textmater/textmater.py
textmater/tools.py
textmater/utils.py
textmater-0.1.dist-info/LICENSE
textmater-0.1.dist-info/METADATA
textmater-0.1.dist-info/WHEEL
textmater-0.1.dist-info/top_level.txt
textmater-0.1.dist-info/RECORD
