Metadata-Version: 2.1
Name: textmater
Version: 0.1
Summary: Extract Structured Data from text
Author-email: Phillip Harry T <philliptinsley44@gmail.com>
License: Apache NON-AI License, Version 2.0
Keywords: text,extract,structured,data,key,value,pair,json,csv,scrape,pdf,ocr
Classifier: License :: Other/Proprietary License
Classifier: Programming Language :: Python
Classifier: Programming Language :: Python :: 3
Classifier: Intended Audience :: Information Technology
Classifier: Intended Audience :: Financial and Insurance Industry
Requires-Python: >=3.8
License-File: LICENSE
